<?xml version="1.0" encoding="UTF-8" standalone="yes"?>
<imgdir name="2020013.img">
    <subprop name="info">
        <subprop name="speak">
            <string name="0" value="n0"/>
            <string name="1" value="n1"/>
        </subprop>
        <subprop name="script">
            <subprop name="0">
                <string name="script" value="pirate3"/>
            </subprop>
        </subprop>
    </subprop>
    <subprop name="stand">
        <canvas name="0" width="71" height="83">
            <vector name="origin" x="41" y="77"/>
            <int name="z" value="0"/>
        </canvas>
    </subprop>
</imgdir>
